dynamus_agent/__init__.py
dynamus_agent/agents/__init__.py
dynamus_agent/agents/agent_base.py
dynamus_agent/agents/capabilities.py
dynamus_agent/agents/exceptions.py
dynamus_agent/communication/__init__.py
dynamus_agent/registry/__init__.py
dynamus_agent/registry/agent_registry.py
dynamus_agent/registry/discovery.py
dynamus_agent/utils/__init__.py
dynamus_agent-0.0.1.dist-info/licenses/LICENSE
dynamus_agent-0.0.1.dist-info/METADATA
dynamus_agent-0.0.1.dist-info/WHEEL
dynamus_agent-0.0.1.dist-info/top_level.txt
dynamus_agent-0.0.1.dist-info/RECORD
