Metadata-Version: 2.4
Name: dynamus-agent
Version: 0.0.1
Summary: Agente base del ecosistema Dynamus para generación y orquestación modular de proyectos.
Author-email: Federico Monfasani <fmonfasani@gmail.com>
License-Expression: MIT
Classifier: Programming Language :: Python :: 3
Classifier: Operating System :: OS Independent
Requires-Python: >=3.9
License-File: LICENSE
Dynamic: license-file
